{"job":{"content":[{"reader":{"name":"kafkacustomreader","parameter":{"topic":"zhaohh1","mode":"earliest-offset","codec":"text","blankIgnore":false,"consumerSettings":{"bootstrap.servers":"49.234.96.157:9092"},"column":[{"name":"a","type":"String"},{"name":"b","type":"String"},{"name":"c","type":"String"}],"separator":","}},"writer":{"name":"hivewriter","parameter":{"maxFileSize":1024,"bufferSize":100,"jdbcUrl":"jdbc:hive2://localhost:10000/zhaohhdb","username":"","password":"","fileType":"parquet","fieldDelimiter":"","writeMode":"append","charsetName":"UTF-8","tablesColumn":"{\"testzhh\":[{\"key\":\"a\",\"type\":\"string\"},{\"key\":\"b\",\"type\":\"string\"},{\"key\":\"c\",\"type\":\"string\"}]}","partition":"pt","partitionType":"MINUTE","defaultFS":"hdfs://namenode:8020"}}}],"setting":{"restore":{"stream":true,"restore":true},"speed":{"readerChannel":1,"writerChannel":1}}}}
